{
	"credit": "Made with Blockbench",
	"textures": {
		"5": "item/pins/hsmpin",
		"particle": "item/pins/hsmpin"
	},
	"elements": [
		{
			"from": [0, 0, 8],
			"to": [16, 16, 8],
			"rotation": {"angle": 0, "axis": "y", "origin": [8, 8, 1]},
			"faces": {
				"north": {"uv": [16, 0, 0, 16], "texture": "#5"},
				"south": {"uv": [0, 0, 16, 16], "texture": "#5"}
			}
		}
	],
	"display": {
		"thirdperson_righthand": {
			"translation": [0, 0, -0.5],
			"scale": [0.3, 0.3, 0.3]
		},
		"thirdperson_lefthand": {
			"scale": [0.3, 0.3, 0.3]
		},
		"firstperson_righthand": {
			"scale": [0.7, 0.7, 0.7]
		},
		"firstperson_lefthand": {
			"scale": [0.7, 0.7, 0.7]
		},
		"fixed": {
			"rotation": [-180, 0, -180]
		}
	}
}